{
  "scope": null,
  "attribute": 9,
  "label": "Theme",
  "type": "Select List",
  "required": "Yes",
  "common": "Yes",
  "showInWizard": "Yes",
  "defaultValue": "STANDARD",
  "displayWidth": null,
  "maximumLength": null,
  "unit": null,
  "minimumColumns": null,
  "maximumColumns": null,
  "dataTypes": null,
  "parentAttributeId": null,
  "lovType": "Static",
  "lovComponentTypeId": null,
  "onDeleteBehavior": null,
  "setTextCase": null,
  "lovNullText": null,
  "userInterface": null,
  "supportedComponentTypes": null,
  "translatable": "No",
  "dependingOn": null,
  "alwaysEvaluate": null,
  "conditionType": null,
  "expression": null,
  "includeColumnsInItemsPicker": "Component",
  "examples": "<p>If you would like to use you own CSS for Spotlight Search, have a look at the included CSS file \"apexspotlight.css\" and override the classes e.g. with Theme Roller.<br>\nExample:</p>\n<pre>\n/* APEX Spotlight Search Orange Theme */\n.apx-Spotlight-result-orange.is-active .apx-Spotlight-link {\n  background-color: #f59e33;\n  color: #fff;\n}\n\n.apx-Spotlight-icon-orange {\n  background-color: #79787e;\n  color: #fff;\n}\n</pre>",
  "helpText": "<p>Choose the Spotlight Search theme which best matches your current UI</p>\n<p>Possible options:<br>\n- Standard: Should be used in most cases, fits very well to Vita theme of UT<br>\n- Orange: Orange list entries with white font and grey icons<br>\n- Red: Red list entries with white font and light grey icons, fits well to Vita Red theme of UT<br></p>\n- Dark: Dark grey list entries with white font and light grey icons, fits well to Vita Dark theme of UT</p>",
  "comment": null
}