{
  "scope": null,
  "attribute": 3,
  "label": "Minimum Input Length",
  "type": "Integer",
  "required": "No",
  "common": "Yes",
  "showInWizard": "Yes",
  "defaultValue": null,
  "displayWidth": 8,
  "maximumLength": null,
  "unit": null,
  "minimumColumns": null,
  "maximumColumns": null,
  "dataTypes": null,
  "parentAttributeId": null,
  "lovType": null,
  "lovComponentTypeId": null,
  "onDeleteBehavior": null,
  "setTextCase": null,
  "lovNullText": null,
  "userInterface": null,
  "supportedComponentTypes": null,
  "translatable": "No",
  "dependingOn": null,
  "alwaysEvaluate": null,
  "conditionType": null,
  "expression": null,
  "includeColumnsInItemsPicker": "Component",
  "examples": null,
  "helpText": "The minimum length for a search term or a new option entered by the user.",
  "comment": null
}